hodgeopera/__init__.py
hodgeopera/layers/__init__.py
hodgeopera/layers/physics.py
hodgeopera/layers/spatial.py
hodgeopera/layers/spectral.py
hodgeopera/models/__init__.py
hodgeopera/models/hybrid.py
hodgeopera/ops/__init__.py
hodgeopera/ops/builder.py
hodgeopera/ops/functional.py
hodgeopera-0.1.0.dist-info/METADATA
hodgeopera-0.1.0.dist-info/WHEEL
hodgeopera-0.1.0.dist-info/top_level.txt
hodgeopera-0.1.0.dist-info/RECORD
