Metadata-Version: 2.4
Name: HodgeOpera
Version: 0.1.0
Summary: Spectral Physics-Aware Neural Operators on Manifolds via Hodge Decomposition
Author: HodgeOpera Team
License: MIT
Keywords: deep-learning,neural-operators,hodge-theory,manifolds,physics-informed
Classifier: Development Status :: 3 - Alpha
Classifier: Intended Audience :: Science/Research
Classifier: License :: OSI Approved :: MIT License
Classifier: Programming Language :: Python :: 3
Classifier: Programming Language :: Python :: 3.8
Classifier: Programming Language :: Python :: 3.9
Classifier: Programming Language :: Python :: 3.10
Classifier: Programming Language :: Python :: 3.11
Classifier: Topic :: Scientific/Engineering :: Artificial Intelligence
Classifier: Topic :: Scientific/Engineering :: Physics
Requires-Python: >=3.8
Requires-Dist: torch>=2.0.0
Requires-Dist: numpy>=1.20.0
Requires-Dist: scipy>=1.7.0
Requires-Dist: toponetx>=0.0.2
Provides-Extra: viz
Requires-Dist: pyvista; extra == "viz"
Requires-Dist: matplotlib; extra == "viz"
Provides-Extra: dev
Requires-Dist: pytest; extra == "dev"
Requires-Dist: black; extra == "dev"
Requires-Dist: flake8; extra == "dev"
